models/__init__.py
models/base_models.py
preprocessing/__init__.py
preprocessing/proprocess.py
trainer/__init__.py
trainer/trainer.py
dl_timeseries-0.0.14.dist-info/LICENSE
dl_timeseries-0.0.14.dist-info/METADATA
dl_timeseries-0.0.14.dist-info/WHEEL
dl_timeseries-0.0.14.dist-info/top_level.txt
dl_timeseries-0.0.14.dist-info/RECORD
