Metadata-Version: 2.1
Name: dl-timeseries
Version: 0.0.14
Summary: Python module for loading time series data.
Home-page: https://github.com/gilberto-BE/dl_timeseries
Author: Gilberto Batres-Estrada
Author-email: g.batres.estrada@gmail.com
License: UNKNOWN
Project-URL: Bug Tracker, https://github.com/gilberto-BE/dl_timeseries/issues
Platform: UNKNOWN
Classifier: Programming Language :: Python :: 3
Classifier: License :: OSI Approved :: MIT License
Classifier: Operating System :: OS Independent
Requires-Python: >=3.6
License-File: LICENSE
